{
  "$schema": "https://raw.githubusercontent.com/OpenLightingProject/open-fixture-library/master/schemas/fixture.json",
  "name": "ACME EYEFLASH 2 RGB (BLINDER 2 RGB) 5ch",
  "shortName": "EYEFLASH 2 （BLINDER 2 RGB）",
  "categories": [
    "Color Changer"
  ],
  "meta": {
    "authors": [
      "GDTF Converter"
    ],
    "createDate": "2023-12-11",
    "lastModifyDate": "2025-10-11",
    "importPlugin": {
      "plugin": "gdtf",
      "date": "2026-06-22",
      "comment": "GDTF v1.2 fixture type ID: 7BC85A46-71ED-4BA4-8D2C-6BE9FB0580A9"
    }
  },
  "comment": "ACME EYEFLASH 2 （BLINDER 2 RGB）: ACME EYEFLASH 2 （BLINDER 2 RGB） ",
  "rdm": {
    "modelId": 33156
  },
  "wheels": {
    "Color1": {
      "slots": [
        {
          "type": "Open",
          "colors": [
            "#ffffff"
          ]
        },
        {
          "type": "Color",
          "name": "Color 1",
          "colors": [
            "#b34a4c"
          ]
        },
        {
          "type": "Color",
          "name": "Color 2",
          "colors": [
            "#e4778d"
          ]
        },
        {
          "type": "Color",
          "name": "Color 3",
          "colors": [
            "#e403b8"
          ]
        },
        {
          "type": "Color",
          "name": "Color 4",
          "colors": [
            "#e435b1"
          ]
        },
        {
          "type": "Color",
          "name": "Color 5",
          "colors": [
            "#e482e4"
          ]
        },
        {
          "type": "Color",
          "name": "Color 6",
          "colors": [
            "#e4d9e4"
          ]
        },
        {
          "type": "Color",
          "name": "Color 7",
          "colors": [
            "#8d01e4"
          ]
        },
        {
          "type": "Color",
          "name": "Color 8",
          "colors": [
            "#6101e4"
          ]
        },
        {
          "type": "Color",
          "name": "Color 9",
          "colors": [
            "#0220e4"
          ]
        },
        {
          "type": "Color",
          "name": "Color 10",
          "colors": [
            "#044be4"
          ]
        },
        {
          "type": "Color",
          "name": "Color 11",
          "colors": [
            "#038de4"
          ]
        },
        {
          "type": "Color",
          "name": "Color 12",
          "colors": [
            "#d9e4e4"
          ]
        },
        {
          "type": "Color",
          "name": "Color 13",
          "colors": [
            "#b8e4e4"
          ]
        },
        {
          "type": "Color",
          "name": "Color 14",
          "colors": [
            "#e4e4e4"
          ]
        },
        {
          "type": "Color",
          "name": "Color 15",
          "colors": [
            "#e4dfce"
          ]
        },
        {
          "type": "Color",
          "name": "Color 16",
          "colors": [
            "#c3e4d9"
          ]
        },
        {
          "type": "Color",
          "name": "Color 17",
          "colors": [
            "#a2e4e4"
          ]
        },
        {
          "type": "Color",
          "name": "Color 18",
          "colors": [
            "#049be4"
          ]
        },
        {
          "type": "Color",
          "name": "Color 19",
          "colors": [
            "#00e4a2"
          ]
        },
        {
          "type": "Color",
          "name": "Color 20",
          "colors": [
            "#03e46c"
          ]
        },
        {
          "type": "Color",
          "name": "Color 21",
          "colors": [
            "#07e400"
          ]
        },
        {
          "type": "Color",
          "name": "Color 22",
          "colors": [
            "#97e44b"
          ]
        },
        {
          "type": "Color",
          "name": "Color 23",
          "colors": [
            "#77db40"
          ]
        },
        {
          "type": "Color",
          "name": "Color 24",
          "colors": [
            "#bcf649"
          ]
        },
        {
          "type": "Color",
          "name": "Color 25",
          "colors": [
            "#b8e44e"
          ]
        },
        {
          "type": "Color",
          "name": "Color 26",
          "colors": [
            "#e4b837"
          ]
        },
        {
          "type": "Color",
          "name": "Color 27",
          "colors": [
            "#e4a22b"
          ]
        },
        {
          "type": "Color",
          "name": "Color 28",
          "colors": [
            "#e48d20"
          ]
        },
        {
          "type": "Color",
          "name": "Color 29",
          "colors": [
            "#e48215"
          ]
        },
        {
          "type": "Color",
          "name": "Color 30",
          "colors": [
            "#e47700"
          ]
        },
        {
          "type": "Color",
          "name": "Color 31",
          "colors": [
            "#e46100"
          ]
        },
        {
          "type": "Color",
          "name": "Color 32",
          "colors": [
            "#e44b00"
          ]
        },
        {
          "type": "Color",
          "name": "Color 33",
          "colors": [
            "#e40100"
          ]
        }
      ]
    },
    "Color2": {
      "slots": [
        {
          "type": "Color",
          "name": "Color 1",
          "colors": [
            "#e40100"
          ]
        },
        {
          "type": "Color",
          "name": "Color 2",
          "colors": [
            "#8f3100"
          ]
        },
        {
          "type": "Color",
          "name": "Color 3",
          "colors": [
            "#a34b25"
          ]
        },
        {
          "type": "Color",
          "name": "Color 4",
          "colors": [
            "#915b1b"
          ]
        },
        {
          "type": "Color",
          "name": "Color 5",
          "colors": [
            "#e4ce4e"
          ]
        },
        {
          "type": "Color",
          "name": "Color 6",
          "colors": [
            "#e4e400"
          ]
        },
        {
          "type": "Color",
          "name": "Color 7",
          "colors": [
            "#cee401"
          ]
        },
        {
          "type": "Color",
          "name": "Color 8",
          "colors": [
            "#b8e400"
          ]
        },
        {
          "type": "Color",
          "name": "Color 9",
          "colors": [
            "#a2e400"
          ]
        },
        {
          "type": "Color",
          "name": "Color 10",
          "colors": [
            "#8de400"
          ]
        },
        {
          "type": "Color",
          "name": "Color 11",
          "colors": [
            "#00e400"
          ]
        },
        {
          "type": "Color",
          "name": "Color 12",
          "colors": [
            "#00e4b8"
          ]
        },
        {
          "type": "Color",
          "name": "Color 13",
          "colors": [
            "#0ae4ce"
          ]
        },
        {
          "type": "Color",
          "name": "Color 14",
          "colors": [
            "#0091e4"
          ]
        },
        {
          "type": "Color",
          "name": "Color 15",
          "colors": [
            "#0577e4"
          ]
        },
        {
          "type": "Color",
          "name": "Color 16",
          "colors": [
            "#0577e4"
          ]
        },
        {
          "type": "Color",
          "name": "Color 17",
          "colors": [
            "#0561e4"
          ]
        },
        {
          "type": "Color",
          "name": "Color 18",
          "colors": [
            "#084be4"
          ]
        },
        {
          "type": "Color",
          "name": "Color 19",
          "colors": [
            "#0735e4"
          ]
        },
        {
          "type": "Color",
          "name": "Color 20",
          "colors": [
            "#0220e4"
          ]
        },
        {
          "type": "Color",
          "name": "Color 21",
          "colors": [
            "#0000e4"
          ]
        },
        {
          "type": "Color",
          "name": "Color 22",
          "colors": [
            "#ce00e4"
          ]
        },
        {
          "type": "Color",
          "name": "Color 23",
          "colors": [
            "#e403b8"
          ]
        },
        {
          "type": "Color",
          "name": "Color 24",
          "colors": [
            "#b806e4"
          ]
        },
        {
          "type": "Color",
          "name": "Color 25",
          "colors": [
            "#ce06e4"
          ]
        },
        {
          "type": "Color",
          "name": "Color 26",
          "colors": [
            "#a205e4"
          ]
        },
        {
          "type": "Color",
          "name": "Color 27",
          "colors": [
            "#e405d9"
          ]
        },
        {
          "type": "Color",
          "name": "Color 28",
          "colors": [
            "#e404e4"
          ]
        },
        {
          "type": "Color",
          "name": "Color 29",
          "colors": [
            "#e405ad"
          ]
        },
        {
          "type": "Color",
          "name": "Color 30",
          "colors": [
            "#e40297"
          ]
        },
        {
          "type": "Color",
          "name": "Color 31",
          "colors": [
            "#e40015"
          ]
        },
        {
          "type": "Color",
          "name": "Color 32",
          "colors": [
            "#e40100"
          ]
        }
      ]
    }
  },
  "availableChannels": {
    "Dim": {
      "highlightValue": 255,
      "capability": {
        "type": "Intensity",
        "brightnessStart": 0,
        "brightnessEnd": 1
      }
    },
    "R": {
      "highlightValue": 255,
      "capability": {
        "type": "ColorIntensity",
        "color": "Red"
      }
    },
    "G": {
      "highlightValue": 255,
      "capability": {
        "type": "ColorIntensity",
        "color": "Green"
      }
    },
    "B": {
      "highlightValue": 255,
      "capability": {
        "type": "ColorIntensity",
        "color": "Blue"
      }
    },
    "Sh1": {
      "highlightValue": 0,
      "capabilities": [
        {
          "dmxRange": [
            0,
            5
          ],
          "type": "ShutterStrobe",
          "helpWanted": "What does physical value 0…1 mean?",
          "comment": "Open 1"
        },
        {
          "dmxRange": [
            6,
            6
          ],
          "type": "ShutterStrobe",
          "shutterEffect": "Strobe",
          "speedStart": "0Hz",
          "speedEnd": "1Hz",
          "comment": "min Strobe"
        },
        {
          "dmxRange": [
            7,
            122
          ],
          "type": "ShutterStrobe",
          "shutterEffect": "Strobe",
          "speedStart": "0Hz",
          "speedEnd": "1Hz"
        },
        {
          "dmxRange": [
            123,
            123
          ],
          "type": "ShutterStrobe",
          "shutterEffect": "Strobe",
          "speedStart": "0Hz",
          "speedEnd": "1Hz",
          "comment": "max Strobe"
        },
        {
          "dmxRange": [
            124,
            127
          ],
          "type": "ShutterStrobe",
          "helpWanted": "What does physical value 0…1 mean?",
          "comment": "Open2"
        },
        {
          "dmxRange": [
            128,
            185
          ],
          "type": "ShutterStrobe",
          "shutterEffect": "Strobe",
          "speedStart": "0Hz",
          "speedEnd": "1Hz",
          "randomTiming": true,
          "comment": "Shutter Ran1"
        },
        {
          "dmxRange": [
            186,
            188
          ],
          "type": "ShutterStrobe",
          "helpWanted": "What does physical value 0…1 mean?",
          "comment": "Open3"
        },
        {
          "dmxRange": [
            189,
            190
          ],
          "type": "ShutterStrobe",
          "helpWanted": "What does physical value 0…1 mean?"
        },
        {
          "dmxRange": [
            191,
            249
          ],
          "type": "ShutterStrobe",
          "shutterEffect": "Strobe",
          "speedStart": "0Hz",
          "speedEnd": "1Hz",
          "randomTiming": true,
          "comment": "Shutter Ran2"
        },
        {
          "dmxRange": [
            250,
            255
          ],
          "type": "ShutterStrobe",
          "helpWanted": "What does physical value 0…1 mean?",
          "comment": "Open4"
        }
      ]
    }
  },
  "modes": [
    {
      "name": "Mode 1 5 DMX ",
      "channels": [
        "Dim",
        "R",
        "G",
        "B",
        "Sh1"
      ]
    }
  ],
  "physical": {
    "dimensions": [
      192,
      145,
      305
    ],
    "weight": 2.5,
    "power": 100,
    "bulb": {
      "type": "Discharge",
      "lumens": 5000,
      "colorTemperature": 3200
    },
    "lens": {
      "degreesMinMax": [
        96.0,
        96.0
      ]
    }
  },
  "gwEmitters": [
    {
      "name": "Red",
      "cie": "0.639900,0.330100,21.280000",
      "hex": "#ff0100"
    },
    {
      "name": "Green",
      "cie": "0.300100,0.599900,71.530000",
      "hex": "#02ff00"
    },
    {
      "name": "Blue",
      "cie": "0.150200,0.060080,7.232000",
      "hex": "#0200ff"
    }
  ],
  "gwSpecs": {
    "description": "ACME EYEFLASH 2 （BLINDER 2 RGB）",
    "beamType": "Wash",
    "operatingTemperature": [
      -10,
      40
    ],
    "revision": {
      "date": "2025-10-11T20:37:58",
      "text": "New fixture type based on ACME EYEFLASH 2 WW (BLINDER 2 RGB) from ACME, Uploaded to GDTF Share."
    }
  },
  "gwMedia": {
    "thumbnail": "4ef2c6fe4b9d3037"
  },
  "manufacturerKey": "maximohfoxy",
  "fixtureKey": "acme-eyeflash-2-rgb-blinder-2-rgb-5ch",
  "gwFixtureTypeID": "7BC85A46-71ED-4BA4-8D2C-6BE9FB0580A9"
}