{
  "$schema": "https://raw.githubusercontent.com/OpenLightingProject/open-fixture-library/master/schemas/fixture.json",
  "name": "AL-RGBW 12x40 ZOOM",
  "shortName": "AL-RGBW 12x40 ZOOM",
  "categories": [
    "Moving Head",
    "Color Changer"
  ],
  "meta": {
    "authors": [
      "GDTF Converter"
    ],
    "createDate": "2023-07-28",
    "lastModifyDate": "2024-06-03",
    "importPlugin": {
      "plugin": "gdtf",
      "date": "2026-06-22",
      "comment": "GDTF v1.2 fixture type ID: 019810A3-CF08-49BB-888E-07E3F7C8DA85"
    }
  },
  "comment": "ALSTERLIGHTS AL-RGBW 12x40 ZOOM",
  "availableChannels": {
    "P": {
      "fineChannelAliases": [
        "P fine"
      ],
      "capabilities": [
        {
          "dmxRange": [
            0,
            0
          ],
          "type": "Pan",
          "angleStart": "0deg",
          "angleEnd": "1deg",
          "comment": "Min"
        },
        {
          "dmxRange": [
            1,
            32895
          ],
          "type": "Pan",
          "angleStart": "0deg",
          "angleEnd": "1deg"
        },
        {
          "dmxRange": [
            32896,
            32896
          ],
          "type": "Pan",
          "angleStart": "0deg",
          "angleEnd": "1deg",
          "comment": "Middle"
        },
        {
          "dmxRange": [
            32897,
            65534
          ],
          "type": "Pan",
          "angleStart": "0deg",
          "angleEnd": "1deg"
        },
        {
          "dmxRange": [
            65535,
            65535
          ],
          "type": "Pan",
          "angleStart": "0deg",
          "angleEnd": "1deg",
          "comment": "Max"
        }
      ]
    },
    "T": {
      "fineChannelAliases": [
        "T fine"
      ],
      "capabilities": [
        {
          "dmxRange": [
            0,
            0
          ],
          "type": "Tilt",
          "angleStart": "0deg",
          "angleEnd": "1deg",
          "comment": "Min"
        },
        {
          "dmxRange": [
            1,
            127
          ],
          "type": "Tilt",
          "angleStart": "0deg",
          "angleEnd": "1deg"
        },
        {
          "dmxRange": [
            128,
            128
          ],
          "type": "Tilt",
          "angleStart": "0deg",
          "angleEnd": "1deg",
          "comment": "Middle"
        },
        {
          "dmxRange": [
            129,
            254
          ],
          "type": "Tilt",
          "angleStart": "0deg",
          "angleEnd": "1deg"
        },
        {
          "dmxRange": [
            255,
            255
          ],
          "type": "Tilt",
          "angleStart": "0deg",
          "angleEnd": "1deg",
          "comment": "Max"
        },
        {
          "dmxRange": [
            256,
            65535
          ],
          "type": "Tilt",
          "angleStart": "0deg",
          "angleEnd": "1deg"
        }
      ]
    },
    "Pos MSpeed": {
      "capability": {
        "type": "PanTiltSpeed",
        "speedStart": 0,
        "speedEnd": 1
      }
    },
    "Zoom": {
      "capabilities": [
        {
          "dmxRange": [
            0,
            0
          ],
          "type": "Zoom",
          "angleStart": "0deg",
          "angleEnd": "1deg",
          "comment": "Zoom wide"
        },
        {
          "dmxRange": [
            1,
            127
          ],
          "type": "Zoom",
          "angleStart": "0deg",
          "angleEnd": "1deg"
        },
        {
          "dmxRange": [
            128,
            128
          ],
          "type": "Zoom",
          "angleStart": "0deg",
          "angleEnd": "1deg",
          "comment": "Zoom Mid"
        },
        {
          "dmxRange": [
            129,
            254
          ],
          "type": "Zoom",
          "angleStart": "0deg",
          "angleEnd": "1deg"
        },
        {
          "dmxRange": [
            255,
            255
          ],
          "type": "Zoom",
          "angleStart": "0deg",
          "angleEnd": "1deg",
          "comment": "Zoom narrow"
        }
      ]
    },
    "Dim": {
      "highlightValue": 255,
      "capability": {
        "type": "Intensity",
        "brightnessStart": 0,
        "brightnessEnd": 1
      }
    },
    "Strobe Rate": {
      "capabilities": [
        {
          "dmxRange": [
            0,
            9
          ],
          "type": "StrobeSpeed",
          "speedStart": 0,
          "speedEnd": 1,
          "comment": "Stop"
        },
        {
          "dmxRange": [
            10,
            255
          ],
          "type": "StrobeSpeed",
          "speedStart": 0,
          "speedEnd": 1,
          "comment": "Slow to fast"
        }
      ]
    },
    "R": {
      "highlightValue": 255,
      "capability": {
        "type": "ColorIntensity",
        "color": "Red"
      }
    },
    "G": {
      "highlightValue": 255,
      "capability": {
        "type": "ColorIntensity",
        "color": "Green"
      }
    },
    "B": {
      "highlightValue": 255,
      "capability": {
        "type": "ColorIntensity",
        "color": "Blue"
      }
    },
    "White": {
      "capability": {
        "type": "ColorIntensity",
        "color": "White"
      }
    },
    "WW": {
      "capability": {
        "type": "ColorIntensity",
        "color": "Warm White"
      }
    },
    "Color Macro1": {
      "capability": {
        "type": "ColorPreset"
      }
    },
    "FX1": {
      "capability": {
        "type": "Effect",
        "effectName": "",
        "speedStart": 0,
        "speedEnd": 1
      }
    },
    "FX2": {
      "capabilities": [
        {
          "dmxRange": [
            0,
            128
          ],
          "type": "EffectSpeed",
          "speedStart": "0Hz",
          "speedEnd": "1Hz",
          "comment": "Forward from slow to fast"
        },
        {
          "dmxRange": [
            129,
            255
          ],
          "type": "EffectSpeed",
          "speedStart": "0Hz",
          "speedEnd": "1Hz",
          "comment": "Reverse from slow to fast"
        }
      ]
    },
    "R 2": {
      "name": "R",
      "capability": {
        "type": "ColorIntensity",
        "color": "Red"
      }
    },
    "G 2": {
      "name": "G",
      "capability": {
        "type": "ColorIntensity",
        "color": "Green"
      }
    },
    "B 2": {
      "name": "B",
      "capability": {
        "type": "ColorIntensity",
        "color": "Blue"
      }
    },
    "White Count": {
      "capability": {
        "type": "Unknown (WhiteCount)",
        "physicalStart": 0,
        "physicalEnd": 1
      }
    },
    "Fixture Global Reset": {
      "capabilities": [
        {
          "dmxRange": [
            0,
            249
          ],
          "type": "Maintenance",
          "parameterStart": 0,
          "parameterEnd": 1,
          "comment": "Safe"
        },
        {
          "dmxRange": [
            250,
            255
          ],
          "type": "Maintenance",
          "parameterStart": 0,
          "parameterEnd": 1,
          "comment": "Reset All"
        }
      ]
    }
  },
  "modes": [
    {
      "name": "Default",
      "channels": [
        "P",
        "P fine",
        "T",
        "T fine",
        "Pos MSpeed",
        "Zoom",
        "Dim",
        "Strobe Rate",
        "R",
        "G",
        "B",
        "White",
        "WW",
        "Color Macro1",
        "FX1",
        "FX2",
        "R 2",
        "G 2",
        "B 2",
        "White Count",
        "Fixture Global Reset"
      ]
    }
  ],
  "physical": {
    "dimensions": [
      120,
      320,
      380
    ],
    "weight": 15.0,
    "power": 1000,
    "bulb": {
      "type": "LED",
      "lumens": 1000,
      "colorTemperature": 6000
    },
    "lens": {
      "degreesMinMax": [
        25.0,
        25.0
      ]
    }
  },
  "gwSpecs": {
    "beamType": "Wash",
    "operatingTemperature": [
      0,
      40
    ],
    "revision": {
      "date": "2024-06-03T15:31:22",
      "text": "V1 2024"
    }
  },
  "gwMedia": {
    "thumbnail": "518250059a014fc3"
  },
  "manufacturerKey": "alsterlights",
  "fixtureKey": "al-rgbw-12x40-zoom",
  "gwFixtureTypeID": "019810A3-CF08-49BB-888E-07E3F7C8DA85"
}