{
  "$schema": "https://raw.githubusercontent.com/OpenLightingProject/open-fixture-library/master/schemas/fixture.json",
  "name": "ACME LASER BAR RGB (LS-608 RGB)",
  "shortName": "LS-608 RGB",
  "categories": [
    "Color Changer"
  ],
  "meta": {
    "authors": [
      "GDTF Converter"
    ],
    "createDate": "2021-07-05",
    "lastModifyDate": "2024-08-28",
    "importPlugin": {
      "plugin": "gdtf",
      "date": "2026-06-22",
      "comment": "GDTF v1.2 fixture type ID: C9A0E078-5FED-465C-96E3-B1EA43AB50D8"
    }
  },
  "comment": "ACME (LASER BAR RGB) LS-608 RGB",
  "availableChannels": {
    "R": {
      "highlightValue": 255,
      "capability": {
        "type": "ColorIntensity",
        "color": "Red"
      }
    },
    "G": {
      "highlightValue": 255,
      "capability": {
        "type": "ColorIntensity",
        "color": "Green"
      }
    },
    "B": {
      "highlightValue": 255,
      "capability": {
        "type": "ColorIntensity",
        "color": "Blue"
      }
    },
    "Dim": {
      "dmxValueResolution": "32bit",
      "highlightValue": 4294967295,
      "capability": {
        "type": "Intensity",
        "brightnessStart": 0,
        "brightnessEnd": 1
      }
    },
    "R 2": {
      "name": "R",
      "highlightValue": 255,
      "capability": {
        "type": "ColorIntensity",
        "color": "Red"
      }
    },
    "G 2": {
      "name": "G",
      "highlightValue": 255,
      "capability": {
        "type": "ColorIntensity",
        "color": "Green"
      }
    },
    "B 2": {
      "name": "B",
      "highlightValue": 255,
      "capability": {
        "type": "ColorIntensity",
        "color": "Blue"
      }
    },
    "Dim 2": {
      "name": "Dim",
      "dmxValueResolution": "32bit",
      "highlightValue": 4294967295,
      "capability": {
        "type": "Intensity",
        "brightnessStart": 0,
        "brightnessEnd": 1
      }
    },
    "R 3": {
      "name": "R",
      "capability": {
        "type": "ColorIntensity",
        "color": "Red"
      }
    },
    "G 3": {
      "name": "G",
      "capability": {
        "type": "ColorIntensity",
        "color": "Green"
      }
    },
    "B 3": {
      "name": "B",
      "capability": {
        "type": "ColorIntensity",
        "color": "Blue"
      }
    },
    "Dim 3": {
      "name": "Dim",
      "dmxValueResolution": "32bit",
      "highlightValue": 4294967295,
      "capability": {
        "type": "Intensity",
        "brightnessStart": 0,
        "brightnessEnd": 1
      }
    },
    "R 4": {
      "name": "R",
      "highlightValue": 255,
      "capability": {
        "type": "ColorIntensity",
        "color": "Red"
      }
    },
    "G 4": {
      "name": "G",
      "highlightValue": 255,
      "capability": {
        "type": "ColorIntensity",
        "color": "Green"
      }
    },
    "B 4": {
      "name": "B",
      "highlightValue": 255,
      "capability": {
        "type": "ColorIntensity",
        "color": "Blue"
      }
    },
    "Dim 4": {
      "name": "Dim",
      "dmxValueResolution": "32bit",
      "highlightValue": 4294967295,
      "capability": {
        "type": "Intensity",
        "brightnessStart": 0,
        "brightnessEnd": 1
      }
    },
    "R 5": {
      "name": "R",
      "highlightValue": 255,
      "capability": {
        "type": "ColorIntensity",
        "color": "Red"
      }
    },
    "G 5": {
      "name": "G",
      "highlightValue": 255,
      "capability": {
        "type": "ColorIntensity",
        "color": "Green"
      }
    },
    "B 5": {
      "name": "B",
      "highlightValue": 255,
      "capability": {
        "type": "ColorIntensity",
        "color": "Blue"
      }
    },
    "Dim 5": {
      "name": "Dim",
      "dmxValueResolution": "32bit",
      "highlightValue": 4294967295,
      "capability": {
        "type": "Intensity",
        "brightnessStart": 0,
        "brightnessEnd": 1
      }
    },
    "R 6": {
      "name": "R",
      "highlightValue": 255,
      "capability": {
        "type": "ColorIntensity",
        "color": "Red"
      }
    },
    "G 6": {
      "name": "G",
      "highlightValue": 255,
      "capability": {
        "type": "ColorIntensity",
        "color": "Green"
      }
    },
    "B 6": {
      "name": "B",
      "highlightValue": 255,
      "capability": {
        "type": "ColorIntensity",
        "color": "Blue"
      }
    },
    "Dim 6": {
      "name": "Dim",
      "dmxValueResolution": "32bit",
      "highlightValue": 4294967295,
      "capability": {
        "type": "Intensity",
        "brightnessStart": 0,
        "brightnessEnd": 1
      }
    },
    "Dim 7": {
      "name": "Dim",
      "highlightValue": 255,
      "capability": {
        "type": "Intensity",
        "brightnessStart": 0,
        "brightnessEnd": 1
      }
    },
    "FX1": {
      "capabilities": [
        {
          "dmxRange": [
            0,
            0
          ],
          "type": "Effect",
          "effectName": "OFF",
          "speed": 0
        },
        {
          "dmxRange": [
            1,
            51
          ],
          "type": "Effect",
          "effectName": "Effects 1",
          "speed": 0
        },
        {
          "dmxRange": [
            52,
            101
          ],
          "type": "Effect",
          "effectName": "Effects 2",
          "speed": 0
        },
        {
          "dmxRange": [
            102,
            152
          ],
          "type": "Effect",
          "effectName": "Effects 3",
          "speed": 0
        },
        {
          "dmxRange": [
            153,
            203
          ],
          "type": "Effect",
          "effectName": "Effects 4",
          "speed": 0
        },
        {
          "dmxRange": [
            204,
            255
          ],
          "type": "Effect",
          "effectName": "Effects 5",
          "speed": 0
        }
      ]
    }
  },
  "modes": [
    {
      "name": "Mode 1  20 DMX",
      "channels": [
        "R",
        "G",
        "B",
        "R 2",
        "G 2",
        "B 2",
        "R 3",
        "G 3",
        "B 3",
        "R 4",
        "G 4",
        "B 4",
        "R 5",
        "G 5",
        "B 5",
        "R 6",
        "G 6",
        "B 6",
        "Dim 7",
        "FX1"
      ]
    },
    {
      "name": "Mode 2  18 DMX",
      "channels": [
        "R",
        "G",
        "B",
        "R 2",
        "G 2",
        "B 2",
        "R 3",
        "G 3",
        "B 3",
        "R 4",
        "G 4",
        "B 4",
        "R 5",
        "G 5",
        "B 5",
        "R 6",
        "G 6",
        "B 6"
      ]
    },
    {
      "name": "Mode 3  5 DMX",
      "channels": [
        "R",
        "G",
        "B",
        "Dim 7",
        "FX1"
      ]
    }
  ],
  "physical": {
    "dimensions": [
      110,
      230,
      1000
    ],
    "weight": 13.8,
    "power": 1000,
    "bulb": {
      "type": "Discharge",
      "lumens": 10000,
      "colorTemperature": 6000
    },
    "lens": {
      "degreesMinMax": [
        1.0,
        1.0
      ]
    }
  },
  "gwEmitters": [
    {
      "name": "Red",
      "cie": "0.640100,0.330000,21.260000",
      "hex": "#ff0000"
    },
    {
      "name": "Green",
      "cie": "0.300100,0.599900,71.530000",
      "hex": "#02ff00"
    },
    {
      "name": "Blue",
      "cie": "0.150000,0.060010,7.220000",
      "hex": "#0000ff"
    }
  ],
  "gwSpecs": {
    "description": "ACME (LASER BAR RGB) LS-608 RGB",
    "beamType": "Spot",
    "operatingTemperature": [
      0,
      40
    ],
    "revision": {
      "date": "2024-08-28T01:43:13",
      "text": "ACME LASER BAR RGB (LS-608 RGB)"
    }
  },
  "gwMedia": {
    "thumbnail": "1ba0d5551f118118"
  },
  "manufacturerKey": "acme",
  "fixtureKey": "acme-laser-bar-rgb-ls-608-rgb",
  "gwFixtureTypeID": "C9A0E078-5FED-465C-96E3-B1EA43AB50D8"
}