{
  "$schema": "https://raw.githubusercontent.com/OpenLightingProject/open-fixture-library/master/schemas/fixture.json",
  "name": "ip storm par",
  "shortName": "IP Storm Par 12",
  "categories": [
    "Color Changer"
  ],
  "meta": {
    "authors": [
      "GDTF Converter"
    ],
    "createDate": "2026-03-14",
    "lastModifyDate": "2026-03-14",
    "importPlugin": {
      "plugin": "gdtf",
      "date": "2026-06-22",
      "comment": "GDTF v1.2 fixture type ID: 0A7BC85E-BE54-42AA-8DF7-236BC80421DF"
    }
  },
  "comment": "Artfox IP Storm Par 12: Battery Powered Par",
  "availableChannels": {
    "Dim": {
      "highlightValue": 255,
      "capability": {
        "type": "Intensity",
        "brightnessStart": 0,
        "brightnessEnd": 1
      }
    },
    "Strobe Rate": {
      "capability": {
        "type": "StrobeSpeed",
        "speedStart": 0,
        "speedEnd": 1
      }
    },
    "Color Macro1": {
      "capability": {
        "type": "ColorPreset"
      }
    },
    "Shaper Macros Speed": {
      "capability": {
        "type": "EffectSpeed",
        "speedStart": 0,
        "speedEnd": 1
      }
    },
    "R": {
      "highlightValue": 255,
      "capability": {
        "type": "ColorIntensity",
        "color": "Red"
      }
    },
    "G": {
      "highlightValue": 255,
      "capability": {
        "type": "ColorIntensity",
        "color": "Green"
      }
    },
    "B": {
      "highlightValue": 255,
      "capability": {
        "type": "ColorIntensity",
        "color": "Blue"
      }
    },
    "White": {
      "capability": {
        "type": "ColorIntensity",
        "color": "White"
      }
    },
    "Amber": {
      "capability": {
        "type": "ColorIntensity",
        "color": "Amber"
      }
    },
    "UV": {
      "capability": {
        "type": "ColorIntensity",
        "color": "UV"
      }
    }
  },
  "modes": [
    {
      "name": "prog",
      "channels": [
        "Dim",
        "Strobe Rate",
        "Color Macro1",
        "Shaper Macros Speed",
        "R",
        "G",
        "B",
        "White",
        "Amber",
        "UV"
      ]
    }
  ],
  "physical": {
    "dimensions": [
      290,
      190,
      290
    ],
    "weight": 4.3,
    "power": 1000,
    "bulb": {
      "type": "Discharge",
      "lumens": 1000,
      "colorTemperature": 6000
    },
    "lens": {
      "degreesMinMax": [
        18.0,
        25.0
      ]
    }
  },
  "gwDmxProfiles": [
    {
      "name": "8ch",
      "points": [
        {
          "DMXPercentage": "0.000000",
          "CFC0": "0.000000",
          "CFC1": "0.000000",
          "CFC2": "0.000000",
          "CFC3": "0.000000"
        },
        {
          "DMXPercentage": "0.000000",
          "CFC0": "0.000000",
          "CFC1": "0.000000",
          "CFC2": "0.000000",
          "CFC3": "0.000000"
        }
      ]
    }
  ],
  "gwSpecs": {
    "description": "Battery Powered Par",
    "beamType": "Wash",
    "operatingTemperature": [
      0,
      40
    ],
    "revision": {
      "date": "2026-03-14T22:00:26",
      "text": "rose par"
    }
  },
  "manufacturerKey": "artfox",
  "fixtureKey": "ip-storm-par",
  "gwFixtureTypeID": "0A7BC85E-BE54-42AA-8DF7-236BC80421DF"
}