{
  "$schema": "https://raw.githubusercontent.com/OpenLightingProject/open-fixture-library/master/schemas/fixture.json",
  "name": "Stage Deck 24x32 at 4ft High",
  "shortName": "24x32 4ft Deck",
  "categories": [
    "Other"
  ],
  "meta": {
    "authors": [
      "GDTF Converter"
    ],
    "importPlugin": {
      "plugin": "gdtf-python-fallback",
      "fixtureTypeID": "A4111962-5DCF-4124-89A9-7AF961CA5EB9"
    }
  },
  "physical": {
    "dimensions": [
      2438,
      1194,
      1219
    ]
  },
  "modes": [],
  "gwSpecs": {
    "description": "4 ft by 8 ft Stage Deck at 4ft High with 1in Perimiter Groove.",
    "operatingTemperature": [
      0,
      40
    ],
    "revision": {
      "date": "2025-08-08T18:59:35",
      "text": "v1_1bo"
    }
  },
  "manufacturerKey": "bakacowpoke",
  "fixtureKey": "stage-deck-24x32-at-4ft-high",
  "gwFixtureTypeID": "A4111962-5DCF-4124-89A9-7AF961CA5EB9",
  "availableChannels": {}
}