{
  "$schema": "https://raw.githubusercontent.com/OpenLightingProject/open-fixture-library/master/schemas/fixture.json",
  "name": "Haze Tour 1500 Oil",
  "shortName": "Haze 1500",
  "categories": [
    "Other"
  ],
  "meta": {
    "authors": [
      "GDTF Converter"
    ],
    "createDate": "2025-08-19",
    "lastModifyDate": "2025-08-27",
    "importPlugin": {
      "plugin": "gdtf",
      "date": "2026-06-22",
      "comment": "GDTF v1.2 fixture type ID: EDD726A4-359A-4F69-8FBD-5D22CAE42977"
    }
  },
  "comment": "PRstage Haze Tour 1500 Oil — a professional oil-based haze machine with 1500 W power. Warm-up time is only 1 minute, output up to 100 m³/min. Features an LCD display, 2 DMX channels, and wireless remote control. Compact (15.3 kg), ideal for tours, concerts, and clubs",
  "availableChannels": {
    "Haze1": {
      "capabilities": [
        {
          "dmxRange": [
            0,
            5
          ],
          "type": "Fog",
          "fogType": "Haze",
          "fogOutput": 0,
          "comment": "Haze Off"
        },
        {
          "dmxRange": [
            6,
            127
          ],
          "type": "Fog",
          "fogType": "Haze",
          "fogOutputStart": 0,
          "fogOutputEnd": 1,
          "comment": "Low Speed Haze"
        },
        {
          "dmxRange": [
            128,
            255
          ],
          "type": "Fog",
          "fogType": "Haze",
          "fogOutputStart": 0,
          "fogOutputEnd": 1,
          "comment": "Hight Speed Haze"
        }
      ]
    },
    "Fan1": {
      "capabilities": [
        {
          "dmxRange": [
            0,
            5
          ],
          "type": "Rotation",
          "speed": 20,
          "comment": "20 percent Speed"
        },
        {
          "dmxRange": [
            6,
            255
          ],
          "type": "Rotation",
          "speedStart": 21,
          "speedEnd": 100,
          "comment": "21 to 100 percent Speed"
        }
      ]
    }
  },
  "modes": [
    {
      "name": "2 Channel Mode ",
      "channels": [
        "Haze1",
        "Fan1"
      ]
    }
  ],
  "physical": {
    "dimensions": [
      250,
      385,
      600
    ],
    "weight": 15.3
  },
  "gwSpecs": {
    "description": "PRstage Haze Tour 1500 Oil — a professional oil-based haze machine with 1500 W power. Warm-up time is only 1 minute, output up to 100 m³/min. Features an LCD display, 2 DMX channels, and wireless remote control. Compact (15.3 kg), ideal for tours, concerts, and clubs",
    "operatingTemperature": [
      0,
      40
    ],
    "revision": {
      "date": "2025-08-27T08:22:08",
      "text": "Ver 1_0"
    }
  },
  "gwMedia": {
    "thumbnail": "4d7b2d28dec6711c"
  },
  "manufacturerKey": "prstage",
  "fixtureKey": "haze-tour-1500-oil",
  "gwFixtureTypeID": "EDD726A4-359A-4F69-8FBD-5D22CAE42977"
}